yomichan-dic/YomitanDic.py
yomichan-dic/__init__.py
yomichandic/YomitanDic.py
yomichandic/__init__.py
yomitandic/__init__.py
yomitandic/yomitandic.py
yomitandic-0.1.8.1.dist-info/METADATA
yomitandic-0.1.8.1.dist-info/WHEEL
yomitandic-0.1.8.1.dist-info/top_level.txt
yomitandic-0.1.8.1.dist-info/RECORD
