Metadata-Version: 2.1
Name: yomitandic
Version: 0.1.8.1
Summary: A library for easily creating dictionary files importable into Yomitan for Japanese popup dictionaries
Author: JawGBoi
Requires-Python: >=3.6
